hesiod/__init__.py
hesiod/cfg/__init__.py
hesiod/cfg/cfghandler.py
hesiod/cfg/cfgparser.py
hesiod/cfg/yamlparser.py
hesiod/core.py
hesiod/py.typed
hesiod/ui/__init__.py
hesiod/ui/tui/__init__.py
hesiod/ui/tui/baseform.py
hesiod/ui/tui/editform.py
hesiod/ui/tui/recapform.py
hesiod/ui/tui/tui.py
hesiod/ui/tui/widgets/__init__.py
hesiod/ui/tui/widgets/custom/__init__.py
hesiod/ui/tui/widgets/custom/datepicker.py
hesiod/ui/tui/widgets/custom/dropdown.py
hesiod/ui/tui/widgets/custom/filebrowser.py
hesiod/ui/tui/widgets/custom/radiobuttons.py
hesiod/ui/tui/widgets/wgtfactory.py
hesiod/ui/tui/widgets/wgthandler.py
hesiod/ui/ui.py
hesiod-1.0.0.dist-info/LICENSE
hesiod-1.0.0.dist-info/WHEEL
hesiod-1.0.0.dist-info/METADATA
hesiod-1.0.0.dist-info/RECORD
