Metadata-Version: 2.1
Name: hesiod
Version: 1.0.0
Summary: 
Author: Luca De Luigi
Author-email: lucadeluigi91@gmail.com
Requires-Python: >=3.6,<3.9
Classifier: Programming Language :: Python :: 3
Classifier: Programming Language :: Python :: 3.6
Classifier: Programming Language :: Python :: 3.7
Classifier: Programming Language :: Python :: 3.8
Requires-Dist: asciimatics (>=1.12.0,<2.0.0)
Requires-Dist: ruamel.yaml (>=0.16.12,<0.17.0)
Requires-Dist: typeguard (>=2.10.0,<3.0.0)
